pyshellpkg/command_dictionary.py
pyshellpkg/command_list.py
pyshellpkg/core_event.py
pyshellpkg/dispatcher.py
pyshellpkg-1.1.dist-info/METADATA
pyshellpkg-1.1.dist-info/WHEEL
pyshellpkg-1.1.dist-info/top_level.txt
pyshellpkg-1.1.dist-info/RECORD
