Metadata-Version: 2.1
Name: pyshellpkg
Version: 1.1
Summary: A simple modular UNIX-like shell using Python
Home-page: https://git.corp.adobe.com/priyanss/python-mini-project
Author: priyanshi
Author-email: priyanss@adobe.com
License: UNKNOWN
Download-URL: https://git.corp.adobe.com/priyanss/python-mini-project/archive/1.2.tar.gz
Keywords: PyShell
Platform: UNKNOWN
Classifier: Environment :: Console
Classifier: Intended Audience :: Developers
Classifier: License :: OSI Approved :: MIT License
Classifier: Operating System :: OS Independent
Classifier: Programming Language :: Python
Classifier: Topic :: Software Development :: Libraries :: Python Modules
